anna_worker/__init__.py
anna_worker/__main__.py
anna_worker/job.py
anna_worker/worker.py
anna_worker-0.0.18.dist-info/METADATA
anna_worker-0.0.18.dist-info/WHEEL
anna_worker-0.0.18.dist-info/top_level.txt
anna_worker-0.0.18.dist-info/RECORD
